calculator_rm.py
calculator_rm-0.1.dist-info/LICENSE
calculator_rm-0.1.dist-info/WHEEL
calculator_rm-0.1.dist-info/METADATA
calculator_rm-0.1.dist-info/RECORD
