Metadata-Version: 2.1
Name: calculator_rm
Version: 0.1
Summary: Calculator class with basic calculator functions
Author-email: Rapolas <rapolas.mikenas@gmail.com>
Requires-Python: >=3.7
Classifier: License :: OSI Approved :: MIT License
